squiz/__init__.py
squiz/squiz.py
squiz-0.3.1.dist-info/LICENSE
squiz-0.3.1.dist-info/METADATA
squiz-0.3.1.dist-info/WHEEL
squiz-0.3.1.dist-info/RECORD
