Metadata-Version: 2.1
Name: squiz
Version: 0.3.1
Summary: View a Python object's direct and nested members.
Home-page: https://github.com/morefigs/squiz/
Author: morefigs
Requires-Python: >=3.10,<4.0
Classifier: Programming Language :: Python :: 3
Classifier: Programming Language :: Python :: 3.10
Classifier: Programming Language :: Python :: 3.11
Classifier: Programming Language :: Python :: 3.12
Requires-Dist: colorama (>=0.4.6,<0.5.0)
